v55pymath.cp312-win_amd64.pyd
v55pymath-0.1.2.dist-info/METADATA
v55pymath-0.1.2.dist-info/WHEEL
v55pymath-0.1.2.dist-info/licenses/LICENSE
v55pymath-0.1.2.dist-info/RECORD
