Metadata-Version: 2.2
Name: v55pymath
Version: 0.1.2
Summary: Math tools including C++ acceleration
Author-Email: Victor Fazyatdenov <soyuznikbu@gmail.com>
